{
  "toolscriptVersion": "1.0.0",
  "version": "43.0.9",
  "pageUuid": "9c8e2756-b433-11f0-89c7-ffca26a519ab",
  "appTemplate": {
    "mobileAppSettings": {
      "object": {
        "displaySetting": {
          "object": {
            "landscapeMode": false,
            "tabletMode": false
          }
        },
        "mobileOfflineModeBannerMode": "default",
        "mobileOfflineModeDelaySync": false,
        "mobileOfflineModeEnabled": false,
        "mobileMultiscreenV2Enabled": true,
        "layoutVersion": 0
      }
    },
    "rootScreen": "tabscreen",
    "isMobileApp": true,
    "version": "3.284.0",
    "multiScreenMobileApp": true,
    "experimentalDataTabEnabled": true
  }
}
